{"area":{"MAP":8,"MATCH":false,"NAME":"Demo_Area","POSITION":"(360.649231, 310.375031)","ROOM":false,"STATE":{"1":{"Enemies/Borboleta3":[true,"(0, 0)"],"Objects/Door":["(0, 0)","(0, 0)"],"Party/Cara":[false,"(0, 0)"],"Treasure/Chest1":true},"10":{},"11":{},"12":{},"13":{},"14":{},"15":{},"2":{"Enemies/Borboleta":[true,"(0, 0)"],"Enemies/Borboleta2":[true,"(0, 0)"],"Enemies/Borboleta3":[true,"(0, 0)"],"Enemies/Borboleta4":[true,"(0, 0)"],"Enemies/Borboleta5":[true,"(0, 0)"],"Enemies/Borboleta6":[true,"(0, 0)"],"Objects/Door":["(0, 0)","(0, 0)"],"Party/Cara":[false,"(0, 0)"],"Treasure/Chest1":true},"3":{"Treasure/Chest1":true},"4":{},"5":{"Enemies/Borboleta":[true,"(0, 0)"],"Enemies/Borboleta2":[true,"(0, 0)"],"Objects/Door":["(736.095032, 6.658999)","(0, 0)"],"Objects/Door2":[true,"(1004.090027, 1.2175)"],"Objects/Door3":["(62.269798, 83.412796)","(0, 0)"],"Objects/Door4":[false,"(54.867302, 607.140015)"],"Objects/Switch":[false,"(595.549011, 206.119995)"],"Objects/Switch2":[false,"(789.060059, 426.826996)"],"Objects/Switch3":[false,"(405.036011, 300.199005)"],"Objects/Switch4":[false,"(502.543976, 459.730988)"],"Party/Cara":[false,"(0, 0)"]},"6":{},"7":{},"8":{"Enemies/Borboleta":[true,"(0, 0)"],"Enemies/Borboleta2":[true,"(0, 0)"],"Enemies/Borboleta3":[true,"(0, 0)"],"Party/Cara":[false,"(0, 0)"]},"9":{}},"TRANSITION":false,"WIN":false},"gold":100,"playtime":443}
